docauto/__init__.py
docauto/cli.py
docauto/config.py
docauto/exceptions.py
docauto/fs.py
docauto/generator.py
docauto/logger.py
docauto/models.py
docauto/parsers.py
docauto/services.py
docauto/tracker.py
docauto/transformers.py
docauto/utils.py
docauto-0.0.2.dist-info/METADATA
docauto-0.0.2.dist-info/WHEEL
docauto-0.0.2.dist-info/entry_points.txt
docauto-0.0.2.dist-info/top_level.txt
docauto-0.0.2.dist-info/RECORD
