Metadata-Version: 2.2
Name: docauto
Version: 0.0.2
Summary: A powerful Python documentation generator that swoops in to automatically create and maintain clean, comprehensive docstrings for your codebase
License: MIT
Requires-Python: >=3.6
Requires-Dist: libcst>=1.6.0
Requires-Dist: openai>=1.64.0
Requires-Dist: tiktoken>=0.9.0
